LICENSE.txt
README.md
setup.cfg
setup.py
./lib/RRGtools/PixSkyTransform.py
./lib/RRGtools/__init__.py
./lib/RRGtools/astro_tools.py
./lib/RRGtools/cluster_member_removal.py
./lib/RRGtools/color_color.py
./lib/RRGtools/match_cat.py
./lib/RRGtools/nearest_neighbour.py
./lib/RRGtools/pysex.py
./lib/RRGtools/pysex_tools.py
./lib/RRGtools/source_extract.py
./lib/asciidata/__init__.py
./lib/asciidata/asciicolumn.py
./lib/asciidata/asciidata.py
./lib/asciidata/asciidata_SExtest.py
./lib/asciidata/asciidata_numtest.py
./lib/asciidata/asciidata_test.py
./lib/asciidata/asciielement.py
./lib/asciidata/asciierror.py
./lib/asciidata/asciifits.py
./lib/asciidata/asciifunction.py
./lib/asciidata/asciiheader.py
./lib/asciidata/asciisorter.py
./lib/asciidata/asciiutils.py
./lib/stilts/stilts.jar
./src/__init__.py
./src/acs_3dpsf.py
./src/acs_determine_focus.py
./src/acs_limits.py
./src/acs_map_xy.py
./src/acs_model_e.py
./src/calc_shear.py
./src/check_external_packages.py
./src/combination.py
./src/directories.py
./src/double_detection_removal.py
./src/drizzle_position.py
./src/ellipse_to_reg.py
./src/getHSTfilter.py
./src/getIndividualExposures.py
./src/interpolate_jwst_psf.py
./src/main.py
./src/masking_star.py
./src/measure_moms.py
./src/mmm.py
./src/plot_shears.py
./src/psf_cor.py
./src/remove_galaxy.py
./src/rotate_moments.py
./src/rrg_to_lenstool.py
./src/setDefaultParams.py
./src/star_galaxy_separation.py
./src/superbit_psf.py
./src/psf_lib/160/TinyTim160.scat
./src/psf_lib/160/TinyTim_f-1.cat
./src/psf_lib/160/TinyTim_f-1.moms
./src/psf_lib/160/TinyTim_f-10.cat
./src/psf_lib/160/TinyTim_f-10.moms
./src/psf_lib/160/TinyTim_f-2.cat
./src/psf_lib/160/TinyTim_f-2.moms
./src/psf_lib/160/TinyTim_f-3.cat
./src/psf_lib/160/TinyTim_f-3.moms
./src/psf_lib/160/TinyTim_f-4.cat
./src/psf_lib/160/TinyTim_f-4.moms
./src/psf_lib/160/TinyTim_f-5.cat
./src/psf_lib/160/TinyTim_f-5.moms
./src/psf_lib/160/TinyTim_f-6.cat
./src/psf_lib/160/TinyTim_f-6.moms
./src/psf_lib/160/TinyTim_f-7.cat
pyRRG.egg-info/PKG-INFO
pyRRG.egg-info/SOURCES.txt
pyRRG.egg-info/dependency_links.txt
pyRRG.egg-info/requires.txt
pyRRG.egg-info/top_level.txt
